Metadata-Version: 2.1
Name: spore.py
Version: 1.1
Summary: Spore REST API client
Home-page: UNKNOWN
Author: LEv145
License: MIT
Project-URL: Git, https://github.com/LEv145/spore.py
Project-URL: Issue tracker, https://github.com/LEv145/spore.py/issues
Platform: UNKNOWN
Requires-Python: >=3.7.0
